aws_lambda_stream/__init__.py
aws_lambda_stream/connectors/__init__.py
aws_lambda_stream/connectors/cloudwatch.py
aws_lambda_stream/connectors/dynamodb.py
aws_lambda_stream/connectors/eventbridge.py
aws_lambda_stream/connectors/lambda_.py
aws_lambda_stream/connectors/opensearch.py
aws_lambda_stream/connectors/s3.py
aws_lambda_stream/connectors/sns.py
aws_lambda_stream/connectors/sqs.py
aws_lambda_stream/events/__init__.py
aws_lambda_stream/events/dynamodb.py
aws_lambda_stream/events/kinesis.py
aws_lambda_stream/events/s3.py
aws_lambda_stream/events/sns.py
aws_lambda_stream/events/sqs.py
aws_lambda_stream/filters/__init__.py
aws_lambda_stream/filters/content.py
aws_lambda_stream/filters/event_type.py
aws_lambda_stream/filters/latch.py
aws_lambda_stream/filters/skip.py
aws_lambda_stream/flavors/__init__.py
aws_lambda_stream/flavors/cdc.py
aws_lambda_stream/flavors/collect.py
aws_lambda_stream/flavors/correlate.py
aws_lambda_stream/flavors/elasticsearch.py
aws_lambda_stream/flavors/evaluate.py
aws_lambda_stream/flavors/materialize.py
aws_lambda_stream/flavors/s3.py
aws_lambda_stream/flavors/sns.py
aws_lambda_stream/flavors/task.py
aws_lambda_stream/pipelines/__init__.py
aws_lambda_stream/repositories/__init__.py
aws_lambda_stream/utils/__init__.py
aws_lambda_stream/utils/apigateway.py
aws_lambda_stream/utils/aws.py
aws_lambda_stream/utils/batch.py
aws_lambda_stream/utils/cloudwatch.py
aws_lambda_stream/utils/concurrency.py
aws_lambda_stream/utils/decorators.py
aws_lambda_stream/utils/dynamodb.py
aws_lambda_stream/utils/elasticsearch.py
aws_lambda_stream/utils/eventbridge.py
aws_lambda_stream/utils/faults.py
aws_lambda_stream/utils/filters.py
aws_lambda_stream/utils/json_encoder.py
aws_lambda_stream/utils/lambda_.py
aws_lambda_stream/utils/logger.py
aws_lambda_stream/utils/operators.py
aws_lambda_stream/utils/opt.py
aws_lambda_stream/utils/pluralize.py
aws_lambda_stream/utils/retry.py
aws_lambda_stream/utils/s3.py
aws_lambda_stream/utils/sns.py
aws_lambda_stream-1.3.1.dist-info/LICENSE
aws_lambda_stream-1.3.1.dist-info/METADATA
aws_lambda_stream-1.3.1.dist-info/WHEEL
aws_lambda_stream-1.3.1.dist-info/RECORD
