Metadata-Version: 2.1
Name: aws_lambda_stream
Version: 1.3.1
Summary: Create stream processors with AWS Lambda functions
Home-page: https://github.com/clandro89/aws-lambda-stream
Author: Alejandro Hernández
Author-email: clandro89@gmail.com
Requires-Python: >=3.8,<4.0
Classifier: Programming Language :: Python :: 3
Classifier: Programming Language :: Python :: 3.8
Classifier: Programming Language :: Python :: 3.9
Classifier: Programming Language :: Python :: 3.10
Classifier: Programming Language :: Python :: 3.11
Classifier: Programming Language :: Python :: 3.12
Classifier: Programming Language :: Python :: 3.13
Requires-Dist: boto3 (>=1.24.66,<2.0.0)
Requires-Dist: pydash (>=5.1.1,<6.0.0)
Requires-Dist: reactivex (>=4.0.4,<5.0.0)
Requires-Dist: requests-aws4auth (>=1.1.2,<2.0.0)
Project-URL: Repository, https://github.com/clandro89/aws-lambda-stream
